setup.cfg
setup.py
mongo_connector/__init__.py
mongo_connector/doc_managers/__init__.py
mongo_connector/doc_managers/error_handler.py
mongo_connector/doc_managers/neo4j_doc_manager.py
mongo_connector/doc_managers/nodes_and_relationships_builder.py
mongo_connector/doc_managers/nodes_and_relationships_updater.py
neo4j_doc_manager.egg-info/PKG-INFO
neo4j_doc_manager.egg-info/SOURCES.txt
neo4j_doc_manager.egg-info/dependency_links.txt
neo4j_doc_manager.egg-info/entry_points.txt
neo4j_doc_manager.egg-info/requires.txt
neo4j_doc_manager.egg-info/top_level.txt