Metadata-Version: 1.1
Name: neo4j-doc-manager
Version: 0.1.1
Summary: Neo4j Doc manager for Mongo Connector
Home-page: https://github.com/neo4j-contrib/neo4j_doc_manager.git
Author: Neo4j Team
Author-email: contact@neo4j.com
License: Apache Software License
Platform: UNKNOWN
Classifier: Development Status :: 5 - Production/Stable
Classifier: Intended Audience :: Developers
Classifier: License :: OSI Approved :: Apache Software License
Classifier: Operating System :: OS Independent
Classifier: Programming Language :: Python :: 2.7
Classifier: Programming Language :: Python :: 3.3
Classifier: Programming Language :: Python :: 3.4
Classifier: Topic :: Database
Classifier: Topic :: Software Development
